viggoparceirov2/__init__.py
viggoparceirov2/resources.py
viggoparceirov2/subsystem/__init__.py
viggoparceirov2/subsystem/parceiro/__init__.py
viggoparceirov2/subsystem/parceiro/controller.py
viggoparceirov2/subsystem/parceiro/manager.py
viggoparceirov2/subsystem/parceiro/resource.py
viggoparceirov2/subsystem/parceiro/router.py
viggoparceirov2/subsystem/parceiro/utils.py
viggoparceirov2/subsystem/parceiro/functions/__init__.py
viggoparceirov2/subsystem/parceiro/functions/entity_create.py
viggoparceirov2/subsystem/parceiro/functions/entity_update.py
viggoparceirov2/subsystem/parceiro/functions/get_usuarios_disponiveis.py
viggoparceirov2/tests/__init__.py
viggoparceirov2/tests/functional/__init__.py
viggoparceirov2/tests/functional/fixtures.py
viggoparceirov2-1.0.5.dist-info/licenses/AUTHORS
viggoparceirov2-1.0.5.dist-info/METADATA
viggoparceirov2-1.0.5.dist-info/WHEEL
viggoparceirov2-1.0.5.dist-info/top_level.txt
viggoparceirov2-1.0.5.dist-info/RECORD
