Metadata-Version: 2.4
Name: viggoparceirov2
Version: 1.0.5
Summary: ViggoParceiroV2 Backend Flask REST service
License-File: AUTHORS
Requires-Dist: viggocorev2<2.0.0,>=1.0.0
Requires-Dist: viggolocalv2>=1.0.0
Requires-Dist: flask-cors
Dynamic: license-file
Dynamic: requires-dist
Dynamic: summary
